Generic_Tree/generic_tree/__init__.py
generic_tree-0.0.1.dist-info/LICENSE
generic_tree-0.0.1.dist-info/METADATA
generic_tree-0.0.1.dist-info/WHEEL
generic_tree-0.0.1.dist-info/entry_points.txt
generic_tree-0.0.1.dist-info/top_level.txt
generic_tree-0.0.1.dist-info/RECORD
